{
  "meta": {
    "id": "在每一滴雨都承载一段记忆的世界里为干旱城市收集最后一滴记忆之雨的人-001",
    "title": "在每一滴雨都承载一段记忆的世界里，为干旱城市收集最后一滴记忆之雨的人",
    "subtitle": "基于真实人生故事改编的沉浸式体验",
    "sourceType": "dingtalk_doc",
    "authorized": true,
    "narrativeTemplate": "hero_journey",
    "createdAt": "2026-06-15T23:47:51+08:00",
    "version": 1
  },
  "events": [
    {
      "id": "evt-01",
      "title": "故事的开始",
      "description": "在每一滴雨都承载一段记忆的世界里，为干旱城市收集最后一滴记忆之雨的人",
      "ageRange": {
        "start": 0,
        "end": 0
      },
      "category": "experience",
      "isKeyNode": false,
      "emotion": "neutral",
      "emotionIntensity": 0.3,
      "narrativeText": "你即将体验「在每一滴雨都承载一段记忆的世界里，为干旱城市收集最后一滴记忆之雨的人」的人生片段。\n\n这是一个关于坚持、选择和成长的故事。",
      "bgmTag": "gentle_folk",
      "visualTone": "warm",
      "sourceAnchor": "交换人生素材剧本库·第192轮·雨水记忆师·类型化虚拟人生"
    }
  ]
}